XNOR_module/__init__.py
xnor_module-0.1.2.dist-info/METADATA
xnor_module-0.1.2.dist-info/WHEEL
xnor_module-0.1.2.dist-info/top_level.txt
xnor_module-0.1.2.dist-info/RECORD
