Metadata-Version: 2.4
Name: XNOR_module
Version: 0.1.2
Summary: Custom encoding/decoding module with CV format and base64
Author-email: Your Name <you@example.com>
License: MIT
Classifier: Programming Language :: Python :: 3
Classifier: License :: OSI Approved :: MIT License
Requires-Python: >=3.8
